{
  "options.showSubtitles": "§4إظهار الترجمة",
  "subtitles.ambient.cave": "§8§oصوط مزعج",
  "subtitles.block.anvil.destroy": "§c§oالسندان تدمر",
  "subtitles.block.anvil.land": "§7§oالسندان وقع",
  "subtitles.block.anvil.use": "§7§oالسندان استعمل",
  "subtitles.block.barrel.close": "§7§oالبرميل يُغلق",
  "subtitles.block.barrel.open": "§7§oالبرميل يُفتح",
  "subtitles.block.beacon.activate": "§b§o§lتنشيط المنارة",
  "subtitles.block.beacon.ambient": "§3§oطنين المنارة",
  "subtitles.block.beacon.deactivate": "§c§o§lمنارة معطلة",
  "subtitles.block.beacon.power_select": "§3§oطاقة المنارة محددة",
  "subtitles.block.beehive.drip": "§6§oيقطر العسل",
  "subtitles.block.beehive.enter": "§7§oنحلة تدخل الخلية",
  "subtitles.block.beehive.exit": "§7§oنحلة خرجت من الخلية",
  "subtitles.block.beehive.shear": "§7§oتكشط المجزات",
  "subtitles.block.beehive.work": "§7§oنحل تعمل",
  "subtitles.block.bell.resonate": "§e§oالجرس يرن",
  "subtitles.block.bell.use": "§c§lدقات الجرس",
  "subtitles.block.blastfurnace.fire_crackle": "§7§oفرن صهر المعادن يتشقق",
  "subtitles.block.brewing_stand.brew": "§7§oمنضدة التخمير تبقبقت",
  "subtitles.block.bubble_column.bubble_pop": "§1§oإنفجار الفقاعات",
  "subtitles.block.bubble_column.upwards_ambient": "§1§oتدفق الفقاعات",
  "subtitles.block.bubble_column.upwards_inside": "§9§oصوت الفقاعات",
  "subtitles.block.bubble_column.whirlpool_ambient": "§1§oدوامة الفقاعات",
  "subtitles.block.bubble_column.whirlpool_inside": "§9§oإهتزاز الفقاعات",
  "subtitles.block.button.click": "§7§oنقر الزر",
  "subtitles.block.campfire.crackle": "§7§oالموقد يتأجج",
  "subtitles.block.chest.close": "§7§oغلق الصندوق",
  "subtitles.block.chest.locked": "§7§lصندوق مغلق",
  "subtitles.block.chest.open": "§7§oفتح الصندوق",
  "subtitles.block.chorus_flower.death": "§5§oزهرة الكورس تذبل",
  "subtitles.block.chorus_flower.grow": "§5§oفاكهة الكورس تنمو",
  "subtitles.block.comparator.click": "§7§oنقرات المقارن",
  "subtitles.block.composter.empty": "§2§oتم تفريغ المُسمِّد",
  "subtitles.block.composter.fill": "§7§oتمت تعبأة المُسمِّد",
  "subtitles.block.composter.ready": "§8§oيقوم المُسمِّد بالتسميد",
  "subtitles.block.conduit.activate": "§b§oالعازل تفعل",
  "subtitles.block.conduit.ambient": "§3§oانبوب ينبض",
  "subtitles.block.conduit.attack.target": "§2§lأنبوب يهجم",
  "subtitles.block.conduit.deactivate": "§c§oأنبوب يتوقف عن العمل",
  "subtitles.block.dispenser.dispense": "§7§oشيء مقذوف",
  "subtitles.block.dispenser.fail": "§4§oفشل القاذف",
  "subtitles.block.door.toggle": "§7§oصرير الباب",
  "subtitles.block.enchantment_table.use": "§e§oاستخدام طاولة التطوير",
  "subtitles.block.end_portal.spawn": "§d§o§lبوابة النهاية تفتح",
  "subtitles.block.end_portal_frame.fill": "§5§oعين الناهي تعلق",
  "subtitles.block.fence_gate.toggle": "§7§oبوابة السياج تصدر الصرير",
  "subtitles.block.fire.ambient": "§7§oاجيج النار",
  "subtitles.block.fire.extinguish": "§7§oاطفئت النار",
  "subtitles.block.furnace.fire_crackle": "§7§oالفرن يخشخش",
  "subtitles.block.generic.break": "§7§oكتلة مكسورة",
  "subtitles.block.generic.footsteps": "§8§oخطوات",
  "subtitles.block.generic.hit": "§7§oكسر الكتلة",
  "subtitles.block.generic.place": "§8§oتم وضع الكتلة",
  "subtitles.block.grindstone.use": "§7§oمجلخة مستخدمة",
  "subtitles.block.honey_block.slide": "§7§oالتزحلق على مكعب عسل",
  "subtitles.block.iron_trapdoor.close": "§7§oالباب الأرضى يُقفل",
  "subtitles.block.iron_trapdoor.open": "§7§oالباب الأرضى يُفتح",
  "subtitles.block.lava.ambient": "§4§oتبقبقت الحمم البركانية",
  "subtitles.block.lava.extinguish": "§2§oالحمم تهسهس",
  "subtitles.block.lever.click": "§7§oمقبض يطق",
  "subtitles.block.note_block.note": "§8§oكتلة الموسيقي تشتغل",
  "subtitles.block.piston.move": "§7§oمكبس يتحرك",
  "subtitles.block.portal.ambient": "§5§oانطلقت بالبوابة",
  "subtitles.block.portal.travel": "§5§oضوضاء البوابة تتلاشى",
  "subtitles.block.portal.trigger": "§d§oضجيج البوابة يزداد",
  "subtitles.block.pressure_plate.click": "§7§oقف على لوح ضغط",
  "subtitles.block.pumpkin.carve": "§8§oمقص الخراف ينحت",
  "subtitles.block.redstone_torch.burnout": "§4§oأزيز شعلة",
  "subtitles.block.respawn_anchor.ambient": "§5§oانطلقت بالبوابة",
  "subtitles.block.respawn_anchor.charge": "§2§oمرساة الإحياء مشحونة",
  "subtitles.block.respawn_anchor.deplete": "§4§oنفدت مرساة الإحياء",
  "subtitles.block.respawn_anchor.set_spawn": "§c§lمرساة الإحياء حددت نقطة الإحياء",
  "subtitles.block.shulker_box.close": "§4§oالشلكر يُغلق",
  "subtitles.block.shulker_box.open": "§4§oالشلكر يُفتح",
  "subtitles.block.smithing_table.use": "§7§oاستخدام طاولة السميثينغ",
  "subtitles.block.smoker.smoke": "§7§oالمدخن يدخن",
  "subtitles.block.trapdoor.toggle": "§7§oفتح الباب الأرضى",
  "subtitles.block.tripwire.attach": "§2§oوُصِل حبل المصيدة",
  "subtitles.block.tripwire.click": "§7§oضغط حبل المصيدة",
  "subtitles.block.tripwire.detach": "§4§oقُطِع حبل المصيدة",
  "subtitles.block.water.ambient": "§1§oالماء يتدفق",
  "subtitles.enchant.thorns.hit": "§c§oوخز الأشواك",
  "subtitles.entity.armor_stand.fall": "§7§oسقط شيء ما",
  "subtitles.entity.arrow.hit": "§f§lسهم يصيب",
  "subtitles.entity.arrow.hit_player": "§4§lضرب لاعب",
  "subtitles.entity.arrow.shoot": "§f§lتم اطلاق السهم",
  "subtitles.entity.bat.ambient": "§8§oصياح الخفافيش",
  "subtitles.entity.bat.death": "§8§o§lالخفاش يموت",
  "subtitles.entity.bat.hurt": "§8§oالخفاش يتأذي",
  "subtitles.entity.bat.takeoff": "§8§oخفاش يحلق",
  "subtitles.entity.bee.ambient": "§8§oطنين النحلة",
  "subtitles.entity.bee.death": "§c§lنحلة ماتت",
  "subtitles.entity.bee.hurt": "§4§oنحلة تأذت",
  "subtitles.entity.bee.loop": "§7§oطنين النحلة",
  "subtitles.entity.bee.loop_aggressive": "§4§oطنين النحلة بغضب",
  "subtitles.entity.bee.pollinate": "§2§oطنين النحلة بسعادة",
  "subtitles.entity.bee.sting": "§4§lلدغ النحلة",
  "subtitles.entity.blaze.ambient": "§4§oالملتهب يتنفس",
  "subtitles.entity.blaze.burn": "§4§oالملتهب يضحك",
  "subtitles.entity.blaze.death": "§a§lالملتهب يموت",
  "subtitles.entity.blaze.hurt": "§2§oالملتهب يتأذي",
  "subtitles.entity.blaze.shoot": "§4§oالملتهب يطلق",
  "subtitles.entity.boat.paddle_land": "§8§oتجديف",
  "subtitles.entity.boat.paddle_water": "§1§oتجديف",
  "subtitles.entity.cat.ambient": "§7§oالقطة تموء",
  "subtitles.entity.cat.beg_for_food": "§7§oالهرة تتوسل",
  "subtitles.entity.cat.death": "§c§lالقطة تموت",
  "subtitles.entity.cat.eat": "§2§oالهرة تأكل",
  "subtitles.entity.cat.hiss": "§4§oالهرة تصدر صوت",
  "subtitles.entity.cat.hurt": "§4§oالقطة تتأذى",
  "subtitles.entity.cat.purr": "§a§oمواء الهرة",
  "subtitles.entity.chicken.ambient": "§8§oكلوكس الدجاج",
  "subtitles.entity.chicken.death": "§a§lالدجاجة تموت",
  "subtitles.entity.chicken.egg": "§7§oالدجاج يسقط",
  "subtitles.entity.chicken.hurt": "§2§oالدجاجة تتأذى",
  "subtitles.entity.cod.death": "§7§lموت سمكة القد",
  "subtitles.entity.cod.flop": "§8§oسمكة القط تخفق",
  "subtitles.entity.cod.hurt": "§8§oسمكة القد تتأذي",
  "subtitles.entity.cow.ambient": "§8§oموس البقر",
  "subtitles.entity.cow.death": "§7§lالبقرة تموت",
  "subtitles.entity.cow.hurt": "§8§oالبقرة تتأذي",
  "subtitles.entity.cow.milk": "§2§oبقرة تُحلب",
  "subtitles.entity.creeper.death": "§a§lالكريبر يموت",
  "subtitles.entity.creeper.hurt": "§2§oكريبر يتأذى",
  "subtitles.entity.creeper.primed": "§c§o§lكريبر يهس",
  "subtitles.entity.dolphin.ambient": "§1§oرغيد الدلفين",
  "subtitles.entity.dolphin.ambient_water": "§1§oتصفير الدلفين",
  "subtitles.entity.dolphin.attack": "§4§oهجوم الدلفين",
  "subtitles.entity.dolphin.death": "§c§lموت الدلفين",
  "subtitles.entity.dolphin.eat": "§2§oأكل الدلفين",
  "subtitles.entity.dolphin.hurt": "§4§oالدلفين يتأذي",
  "subtitles.entity.dolphin.jump": "§1§oقفز الدلفين",
  "subtitles.entity.dolphin.play": "§2§oلعب الدلفين",
  "subtitles.entity.dolphin.splash": "§1§oرذاذ الدلفين",
  "subtitles.entity.dolphin.swim": "§1§oسباحة الدلفين",
  "subtitles.entity.donkey.ambient": "§7§oحمار ينهق",
  "subtitles.entity.donkey.angry": "§4§oحمار neighs",
  "subtitles.entity.donkey.chest": "§2§lصدر الحمار مزود",
  "subtitles.entity.donkey.death": "§c§lمات الحمار",
  "subtitles.entity.donkey.eat": "§2§oالحمار يأكل",
  "subtitles.entity.donkey.hurt": "§4§oالحمار يتأذي",
  "subtitles.entity.drowned.ambient": "§4§oغرغرة الغارق",
  "subtitles.entity.drowned.ambient_water": "§4§oغرغرة الغارق",
  "subtitles.entity.drowned.death": "§2§lموت الغارق",
  "subtitles.entity.drowned.hurt": "§2§oتأذي الغارق",
  "subtitles.entity.drowned.shoot": "§4§o§lرمي الغارق للرمح",
  "subtitles.entity.drowned.step": "§4§oخطوات الغارق",
  "subtitles.entity.drowned.swim": "§4§oالغارق يسبح",
  "subtitles.entity.egg.throw": "§7§lبيضة تطير",
  "subtitles.entity.elder_guardian.ambient": "§4§oالحارس الأقدم يأن",
  "subtitles.entity.elder_guardian.ambient_land": "§4§oالحارس الأقدم يذعر",
  "subtitles.entity.elder_guardian.curse": "§c§o§lالحارس الأقدم يسب",
  "subtitles.entity.elder_guardian.death": "§a§lالحارس الأقدم يموت",
  "subtitles.entity.elder_guardian.flop": "§2§oالحارس الأقدم يذعر",
  "subtitles.entity.elder_guardian.hurt": "§2§oالحارس الأقدم يتأذى",
  "subtitles.entity.ender_dragon.ambient": "§5§oتنين يزأر",
  "subtitles.entity.ender_dragon.death": "§b§o§lتنين يموت",
  "subtitles.entity.ender_dragon.flap": "§d§lتنين يرفرف",
  "subtitles.entity.ender_dragon.growl": "§5§oتنين يهدر",
  "subtitles.entity.ender_dragon.hurt": "§2§oالتنين يتأذي",
  "subtitles.entity.ender_dragon.shoot": "§d§o§lتنين يطلق",
  "subtitles.entity.ender_eye.death": "§7§oعين الناهي تسقط",
  "subtitles.entity.ender_eye.launch": "§7§lاطلاق عين ايندر",
  "subtitles.entity.ender_pearl.throw": "§7§oطيران لؤلؤة الاندر",
  "subtitles.entity.enderman.ambient": "§5§oفووبس اندرمان",
  "subtitles.entity.enderman.death": "§a§lاندرمان يموت",
  "subtitles.entity.enderman.hurt": "§2§oتألم الاندرمان",
  "subtitles.entity.enderman.stare": "§4§oصزاخ الاندرمان",
  "subtitles.entity.enderman.teleport": "§5§lانتقال الاندرمان",
  "subtitles.entity.endermite.ambient": "§4§oحشرة الأندر تندفع",
  "subtitles.entity.endermite.death": "§a§lحشرة الأندر تموت",
  "subtitles.entity.endermite.hurt": "§2§oحشرة الأندر تتأذي",
  "subtitles.entity.evoker.ambient": "§4§oالمدعي الساحر يدندن",
  "subtitles.entity.evoker.cast_spell": "§c§o§lالمدعي الساحر يلقي تعويذة",
  "subtitles.entity.evoker.celebrate": "§4§oهتافات Evoker",
  "subtitles.entity.evoker.death": "§a§lالمدعي الساحر يموت",
  "subtitles.entity.evoker.hurt": "§2§oالمدعي الساحر يتأذي",
  "subtitles.entity.evoker.prepare_attack": "§4§oالمدعي الساحر يستعد للهجوم",
  "subtitles.entity.evoker.prepare_summon": "§4§oالمدعي الساحر يحضّر الاستدعاء",
  "subtitles.entity.evoker.prepare_wololo": "§4§oالمدعي الساحر يحضّر سحر",
  "subtitles.entity.evoker_fangs.attack": "§c§lعضة الأنياب",
  "subtitles.entity.experience_orb.pickup": "§2§oالخبرة المكتسبة",
  "subtitles.entity.firework_rocket.blast": "§7§oانفجارات الالعاب النارية",
  "subtitles.entity.firework_rocket.launch": "§8§oاطلاق الالعاب النارية",
  "subtitles.entity.firework_rocket.twinkle": "§e§oيسكن العيون وابتهالات ترتعش الالعاب النارية",
  "subtitles.entity.fishing_bobber.retrieve": "§8§oتم إسترجاع الطُعم",
  "subtitles.entity.fishing_bobber.splash": "§7§lرذاذ الصيد",
  "subtitles.entity.fishing_bobber.throw": "§8§oألقيت عوامة",
  "subtitles.entity.fox.aggro": "§4§oالثعلب يغضب",
  "subtitles.entity.fox.ambient": "§8§oالثعلب صرير",
  "subtitles.entity.fox.bite": "§4§lالثعلب يعض",
  "subtitles.entity.fox.death": "§c§o§lالثعلب يموت",
  "subtitles.entity.fox.eat": "§2§oالثعلب يأكل",
  "subtitles.entity.fox.hurt": "§4§oالثعلب يتأذي",
  "subtitles.entity.fox.screech": "§7§oالثعلب يصيح",
  "subtitles.entity.fox.sleep": "§8§oالثلعب ينام",
  "subtitles.entity.fox.sniff": "§8§oالثعلب يشم",
  "subtitles.entity.fox.spit": "§2§oالثعلب يبصق",
  "subtitles.entity.fox.teleport": "§5§lالثعلب ينتقل",
  "subtitles.entity.generic.big_fall": "§7§oسقط شئ ما",
  "subtitles.entity.generic.burn": "§c§oالاحتراق",
  "subtitles.entity.generic.death": "§f§lيموت",
  "subtitles.entity.generic.drink": "§2§oيحتسي",
  "subtitles.entity.generic.eat": "§2§oيتناول الطعام",
  "subtitles.entity.generic.explode": "§f§lانفجار",
  "subtitles.entity.generic.extinguish_fire": "§7§oحريقة تطفأ",
  "subtitles.entity.generic.hurt": "§f§oشيء تألم",
  "subtitles.entity.generic.small_fall": "§f§oسقط شيء ما",
  "subtitles.entity.generic.splash": "§1§oرش",
  "subtitles.entity.generic.swim": "§1§oسباحة",
  "subtitles.entity.ghast.ambient": "§4§oالشبح يبكي",
  "subtitles.entity.ghast.death": "§a§lالشبح مات",
  "subtitles.entity.ghast.hurt": "§2§oالشبح يتأذى",
  "subtitles.entity.ghast.shoot": "§4§oالشبح يطلق نارًا",
  "subtitles.entity.guardian.ambient": "§4§oسمكة الحارس تأن",
  "subtitles.entity.guardian.ambient_land": "§4§oسمكة الحارس تخفق",
  "subtitles.entity.guardian.attack": "§c§lسمكة الحارس تطلق",
  "subtitles.entity.guardian.death": "§a§lيموت الوصي",
  "subtitles.entity.guardian.flop": "§2§oسمكة الحارس تخفق",
  "subtitles.entity.guardian.hurt": "§2§oيسيء الوصي",
  "subtitles.entity.hoglin.ambient": "§4§oHoglin يزمجر",
  "subtitles.entity.hoglin.angry": "§c§oHoglin يزمجر بغضب",
  "subtitles.entity.hoglin.attack": "§c§lHoglin يهاجم",
  "subtitles.entity.hoglin.converted_to_zombified": "§4§oHoglin يتحول إلى Zoglin",
  "subtitles.entity.hoglin.death": "§a§lHoglin مات",
  "subtitles.entity.hoglin.hurt": "§2§oHoglin يتأذى",
  "subtitles.entity.hoglin.retreat": "§2§oHoglin يتراجع",
  "subtitles.entity.hoglin.step": "§4§oخطوات الHoglin",
  "subtitles.entity.horse.ambient": "§7§oالخيل يصهل",
  "subtitles.entity.horse.angry": "§4§oصهيل الفرس",
  "subtitles.entity.horse.armor": "§2§lارتدي درع الحصان",
  "subtitles.entity.horse.breathe": "§8§oالخيل يتنفس",
  "subtitles.entity.horse.death": "§c§o§lالخيل يموت",
  "subtitles.entity.horse.eat": "§2§oالخيل يأكل",
  "subtitles.entity.horse.gallop": "§7§oجالت الخيل",
  "subtitles.entity.horse.hurt": "§4§oالخيل يتأذي",
  "subtitles.entity.horse.jump": "§7§oالخيل يقفز",
  "subtitles.entity.horse.saddle": "§2§lالسرج يزود",
  "subtitles.entity.husk.ambient": "§4§oقشر اهات",
  "subtitles.entity.husk.converted_to_zombie": "§4§oيتحول Husk إلى زومبي",
  "subtitles.entity.husk.death": "§a§lيموت قشر",
  "subtitles.entity.husk.hurt": "§2§oيسيء قشر",
  "subtitles.entity.illusioner.ambient": "§4§oيدندن الإيلوسيونير",
  "subtitles.entity.illusioner.cast_spell": "§c§lإيلوسيونير يلقي التعويذة",
  "subtitles.entity.illusioner.death": "§a§lيموت الإيلوسيونير",
  "subtitles.entity.illusioner.hurt": "§2§oيصاب الإيلوسيونير",
  "subtitles.entity.illusioner.mirror_move": "§4§oينزاح الإيلوسيونير",
  "subtitles.entity.illusioner.prepare_blindness": "§4§oالإيلوسيونير يحضّر العمى",
  "subtitles.entity.illusioner.prepare_mirror": "§4§oالإيلوسيونير يحضّر صورة مطابقة للأصل",
  "subtitles.entity.iron_golem.attack": "§f§lالغولم الحديدي يهجم",
  "subtitles.entity.iron_golem.damage": "§4§o§lغولم حديدي يتحطم",
  "subtitles.entity.iron_golem.death": "§c§lالغولم الحديدي يموت",
  "subtitles.entity.iron_golem.hurt": "§4§oالغولم الحديدي يتأذي",
  "subtitles.entity.iron_golem.repair": "§a§oتم إصلاح الغولم الحديدي",
  "subtitles.entity.item.break": "§c§lفواصل البند",
  "subtitles.entity.item.pickup": "§7§oأداة تسقط",
  "subtitles.entity.item_frame.add_item": "§8§oيملأ الإطار البند",
  "subtitles.entity.item_frame.break": "§7§oالبند فواصل الإطار",
  "subtitles.entity.item_frame.place": "§8§oوضع إطار البند",
  "subtitles.entity.item_frame.remove_item": "§7§oيصب في إطار البند",
  "subtitles.entity.item_frame.rotate_item": "§8§oعنصر الإطار بالنقر فوق",
  "subtitles.entity.leash_knot.break": "§4§oفواصل المقود عقدة",
  "subtitles.entity.leash_knot.place": "§2§oمقود عقدة ربطت",
  "subtitles.entity.lightning_bolt.impact": "§f§lالضربات الإضاءة",
  "subtitles.entity.lightning_bolt.thunder": "§7§oالتقارير السنوية الرعد",
  "subtitles.entity.llama.ambient": "§7§oثغاء اللاما",
  "subtitles.entity.llama.angry": "§4§oثغاء اللاما الغاضبة",
  "subtitles.entity.llama.chest": "§2§lمعدات خرج اللاما",
  "subtitles.entity.llama.death": "§c§lلاما تموت",
  "subtitles.entity.llama.eat": "§2§oلاما تأكل",
  "subtitles.entity.llama.hurt": "§4§oلاما تتأذى",
  "subtitles.entity.llama.spit": "§f§lلاما تبصق",
  "subtitles.entity.llama.step": "§8§oلاما تمشي",
  "subtitles.entity.llama.swag": "§2§lاللاما تم تزينها",
  "subtitles.entity.magma_cube.death": "§a§lمكعب الصهارة يموت",
  "subtitles.entity.magma_cube.hurt": "§2§oمكعب الصهارة يتأذي",
  "subtitles.entity.magma_cube.squish": "§4§oمكعب الصهارة يُسحق",
  "subtitles.entity.minecart.riding": "§7§oلفات مينيكارت",
  "subtitles.entity.mooshroom.convert": "§7§lبقرة المشروم تتحول",
  "subtitles.entity.mooshroom.eat": "§2§oبقرة الموشروم تأكل",
  "subtitles.entity.mooshroom.milk": "§2§oبقرة المشروم تحلب",
  "subtitles.entity.mooshroom.suspicious_milk": "§2§oبقرة المشروم تحلب بشكل مثير للريبة",
  "subtitles.entity.mule.ambient": "§7§oهاوس بغل",
  "subtitles.entity.mule.angry": "§4§oصهيل البغل",
  "subtitles.entity.mule.chest": "§2§lمعدات سرج البغل",
  "subtitles.entity.mule.death": "§c§lيموت بغل",
  "subtitles.entity.mule.eat": "§2§oالبغل يأكل",
  "subtitles.entity.mule.hurt": "§4§oيضر بغل",
  "subtitles.entity.painting.break": "§8§oفواصل اللوحة",
  "subtitles.entity.painting.place": "§8§oاللوحة الموضوعة",
  "subtitles.entity.panda.aggressive_ambient": "§4§oدب الباندا غضب",
  "subtitles.entity.panda.ambient": "§7§oالباندا يلهث",
  "subtitles.entity.panda.bite": "§4§lالباندا يعض",
  "subtitles.entity.panda.cant_breed": "§4§oالباندا يثغي",
  "subtitles.entity.panda.death": "§c§o§lالباندا يموت",
  "subtitles.entity.panda.eat": "§2§oالباندا يأكل",
  "subtitles.entity.panda.hurt": "§4§oالباندا يتألم",
  "subtitles.entity.panda.pre_sneeze": "§8§oأنف الباندا يتدغدغ",
  "subtitles.entity.panda.sneeze": "§7§oالباندا يعطس",
  "subtitles.entity.panda.step": "§8§oالباندا يخطو",
  "subtitles.entity.panda.worried_ambient": "§8§oالباندا ينشج",
  "subtitles.entity.parrot.ambient": "§7§oالببغاء يتكلم",
  "subtitles.entity.parrot.death": "§c§lمات الببغاء",
  "subtitles.entity.parrot.eats": "§2§oيأكل الببغاء",
  "subtitles.entity.parrot.fly": "§7§oالببغاء بطفو في الهواء",
  "subtitles.entity.parrot.hurts": "§4§oالببغاء يتأذي",
  "subtitles.entity.parrot.imitate.blaze": "§7§oالببغاء يلهث",
  "subtitles.entity.parrot.imitate.creeper": "§7§oهسهسة الببغاء",
  "subtitles.entity.parrot.imitate.drowned": "§7§oغرغرة الببغاء",
  "subtitles.entity.parrot.imitate.elder_guardian": "§7§oيرفرف الببغاء",
  "subtitles.entity.parrot.imitate.ender_dragon": "§7§oيضج الببغاء",
  "subtitles.entity.parrot.imitate.endermite": "§7§oالببغاء يندفع",
  "subtitles.entity.parrot.imitate.evoker": "§7§oالببغاء يدمدم",
  "subtitles.entity.parrot.imitate.ghast": "§7§oالببغاء يبكي",
  "subtitles.entity.parrot.imitate.guardian": "§7§oنقيق الببغاء",
  "subtitles.entity.parrot.imitate.hoglin": "§7§ooهدير الببغاء",
  "subtitles.entity.parrot.imitate.husk": "§7§oيأن الببغاء",
  "subtitles.entity.parrot.imitate.illusioner": "§7§oيدمدم الببغاء",
  "subtitles.entity.parrot.imitate.magma_cube": "§7§oالببغاء يُسحق",
  "subtitles.entity.parrot.imitate.phantom": "§7§oصياح الببغاء",
  "subtitles.entity.parrot.imitate.piglin": "§7§oشخير الببغاء",
  "subtitles.entity.parrot.imitate.piglin_brute": "§7§oالببغاء الشخير بقوة",
  "subtitles.entity.parrot.imitate.pillager": "§7§oالببغاء يدمدم",
  "subtitles.entity.parrot.imitate.ravager": "§7§oيهمهم الببغاء",
  "subtitles.entity.parrot.imitate.shulker": "§7§oيتخفى الببغاء",
  "subtitles.entity.parrot.imitate.silverfish": "§7§oالببغاء يهسهس",
  "subtitles.entity.parrot.imitate.skeleton": "§7§oيخشخش الببغاء",
  "subtitles.entity.parrot.imitate.slime": "§7§oببغاء يسحق",
  "subtitles.entity.parrot.imitate.spider": "§7§oهسهسة الببغاء",
  "subtitles.entity.parrot.imitate.stray": "§7§oيخشخش الببغاء",
  "subtitles.entity.parrot.imitate.vex": "§7§oيغيظ الببغاء",
  "subtitles.entity.parrot.imitate.vindicator": "§7§oيدمدم الببغاء",
  "subtitles.entity.parrot.imitate.witch": "§7§oيقهقه الببغاء",
  "subtitles.entity.parrot.imitate.wither": "§7§oيغضب الببغاء",
  "subtitles.entity.parrot.imitate.wither_skeleton": "§7§oخشخشة الببغاء",
  "subtitles.entity.parrot.imitate.zoglin": "§7§oهدير الببغاء",
  "subtitles.entity.parrot.imitate.zombie": "§7§oيأن الببغاء",
  "subtitles.entity.parrot.imitate.zombie_villager": "§7§oيأن الببغاء",
  "subtitles.entity.phantom.ambient": "§4§oصياح الطيف",
  "subtitles.entity.phantom.bite": "§4§lلدغات الطيف",
  "subtitles.entity.phantom.death": "§a§lموت الطيف",
  "subtitles.entity.phantom.flap": "§4§oخفق الطيف",
  "subtitles.entity.phantom.hurt": "§2§oالطيف يتأذي",
  "subtitles.entity.phantom.swoop": "§4§oوثب الطيف",
  "subtitles.entity.pig.ambient": "§8§oأوينكس الخنازير",
  "subtitles.entity.pig.death": "§7§lيموت الخنزير",
  "subtitles.entity.pig.hurt": "§2§oيسيء خنزير",
  "subtitles.entity.pig.saddle": "§2§lالسرج يزود",
  "subtitles.entity.piglin.admiring_item": "§2§oبيجلن يعجب بالغرض",
  "subtitles.entity.piglin.ambient": "§8§oشخير بيجلن",
  "subtitles.entity.piglin.angry": "§4§oبيجلن يشخر بغضب",
  "subtitles.entity.piglin.celebrate": "§2§oبيجلن يحتفل",
  "subtitles.entity.piglin.converted_to_zombified": "§4§oبيجلن تحول الى بيجلن الزومبي",
  "subtitles.entity.piglin.death": "§a§lبيجلن يموت",
  "subtitles.entity.piglin.hurt": "§2§oبيجلن يؤذي",
  "subtitles.entity.piglin.jealous": "§7§oبيجلن يشخر بحسد",
  "subtitles.entity.piglin.retreat": "§2§oبيجلن يتراجع",
  "subtitles.entity.piglin.step": "§8§oخطوات بيجلن",
  "subtitles.entity.piglin_brute.ambient": "§4§oبيجلن يشخر بغضب",
  "subtitles.entity.piglin_brute.angry": "§c§oبيجلن يشخر بغضب",
  "subtitles.entity.piglin_brute.death": "§2§lبيجلن يشخر بغضب",
  "subtitles.entity.piglin_brute.hurt": "§2§oبيجلن يشخر بغضب",
  "subtitles.entity.piglin_brute.step": "§4§oبيجلن يشخر بغضب",
  "subtitles.entity.piglin_brute.converted_to_zombified": "§4§oبيجلن تحول الى بيجلن الزومبي",
  "subtitles.entity.pillager.ambient": "§4§oالناهب يهمهم",
  "subtitles.entity.pillager.celebrate": "§4§oالناهب يهتف",
  "subtitles.entity.pillager.death": "§a§lالناهب يموت",
  "subtitles.entity.pillager.hurt": "§2§oالناهب يتأذي",
  "subtitles.entity.player.attack.crit": "§f§o§lهجوم تكتيكي",
  "subtitles.entity.player.attack.knockback": "§f§o§lهجوم الطرح",
  "subtitles.entity.player.attack.strong": "§f§o§lهجوم القوة",
  "subtitles.entity.player.attack.sweep": "§f§o§lهجوم الكنس",
  "subtitles.entity.player.attack.weak": "§7§o§lهجوم ضعيف",
  "subtitles.entity.player.burp": "§8§oتجشؤ",
  "subtitles.entity.player.death": "§c§lلاعب يموت",
  "subtitles.entity.player.hurt": "§4§lلاعب يسيء",
  "subtitles.entity.player.hurt_drown": "§4§lلاعب يغرق",
  "subtitles.entity.player.hurt_on_fire": "§4§lلاعب يحترق",
  "subtitles.entity.player.levelup": "§a§lلاعب الضربات",
  "subtitles.entity.polar_bear.ambient": "§7§oاهات الدب القطبي",
  "subtitles.entity.polar_bear.ambient_baby": "§7§oحمص الدب القطبي",
  "subtitles.entity.polar_bear.death": "§c§lيموت الدب القطبي",
  "subtitles.entity.polar_bear.hurt": "§4§oيسيء الدب القطبي",
  "subtitles.entity.polar_bear.warning": "§4§oالدب القطبي التقارير السنوية",
  "subtitles.entity.potion.splash": "§f§lيحطم زجاجة",
  "subtitles.entity.potion.throw": "§f§lزجاجة ألقيت",
  "subtitles.entity.puffer_fish.blow_out": "§4§oتفرغ السمكة المنتفخة",
  "subtitles.entity.puffer_fish.blow_up": "§4§oإنتفاخ السمكة المنتفخة",
  "subtitles.entity.puffer_fish.death": "§a§lالسمكة المنتفخة تموت",
  "subtitles.entity.puffer_fish.flop": "§2§oالسمكة المنتفخة تخفق",
  "subtitles.entity.puffer_fish.hurt": "§2§oالسمكة المنتفخة تتأذي",
  "subtitles.entity.puffer_fish.sting": "§4§lوخز السمكة المنتفخة",
  "subtitles.entity.rabbit.ambient": "§8§oالأرنب الصرير",
  "subtitles.entity.rabbit.attack": "§c§lالهجمات الأرنب",
  "subtitles.entity.rabbit.death": "§a§lيموت الأرنب",
  "subtitles.entity.rabbit.hurt": "§a§oيسيء الأرنب",
  "subtitles.entity.rabbit.jump": "§8§oأرنب القفزات",
  "subtitles.entity.ravager.ambient": "§4§oالوحش القروي يهمهم",
  "subtitles.entity.ravager.attack": "§c§lالوحش القروي يعض",
  "subtitles.entity.ravager.celebrate": "§4§oالوحش القروي يهتف",
  "subtitles.entity.ravager.death": "§a§lالوحش القروي يموت",
  "subtitles.entity.ravager.hurt": "§2§oالوحش القروي يتأذي",
  "subtitles.entity.ravager.roar": "§4§oالوحش القروي يزئر",
  "subtitles.entity.ravager.step": "§4§oالوحش القروي يخطو",
  "subtitles.entity.ravager.stunned": "§2§oالوحش القروي متفاجئ",
  "subtitles.entity.salmon.death": "§7§lموت سمكة السلمون",
  "subtitles.entity.salmon.flop": "§8§oسمكة السلمون تخفق",
  "subtitles.entity.salmon.hurt": "§8§oسمكة السلمون تتأذي",
  "subtitles.entity.sheep.ambient": "§8§oبأس الأغنام",
  "subtitles.entity.sheep.death": "§7§lوفاة الأغنام",
  "subtitles.entity.sheep.hurt": "§2§oيسيء الأغنام",
  "subtitles.entity.shulker.ambient": "§4§oالشلكر يتربص",
  "subtitles.entity.shulker.close": "§4§oشولكير يغلق",
  "subtitles.entity.shulker.death": "§a§lالشلكر يموت",
  "subtitles.entity.shulker.hurt": "§2§oالشلكر يتأذي",
  "subtitles.entity.shulker.open": "§4§oشولكير يفتح",
  "subtitles.entity.shulker.shoot": "§4§oالشلكر يطلق",
  "subtitles.entity.shulker.teleport": "§5§lالشلكر يتنقل",
  "subtitles.entity.shulker_bullet.hit": "§2§oقذيفة الشلكر تنفجر",
  "subtitles.entity.shulker_bullet.hurt": "§4§oقذيفة الشلكر تنكسر",
  "subtitles.entity.silverfish.ambient": "§4§oحشرة السمكة الفضية تهسهس",
  "subtitles.entity.silverfish.death": "§a§lحشرة السمكة الفضية تموت",
  "subtitles.entity.silverfish.hurt": "§2§oحشرة السمكة الفضية تتأذي",
  "subtitles.entity.skeleton.ambient": "§4§oسكلتون بيحدث صوت",
  "subtitles.entity.skeleton.death": "§a§lسكلتون يموت",
  "subtitles.entity.skeleton.hurt": "§2§oسكلتون يتأذي",
  "subtitles.entity.skeleton.shoot": "§4§lيطلق النار على هيكل عظمى",
  "subtitles.entity.skeleton_horse.ambient": "§7§oصرخات الخيل العظمي",
  "subtitles.entity.skeleton_horse.death": "§c§lالخيل العظمي يموت",
  "subtitles.entity.skeleton_horse.hurt": "§4§oالخيل العظمي يتأذي",
  "subtitles.entity.skeleton_horse.swim": "§9§oالخيل العظمي يسبح",
  "subtitles.entity.slime.attack": "§4§lالهجمات الوحل",
  "subtitles.entity.slime.death": "§a§lيموت الوحل",
  "subtitles.entity.slime.hurt": "§2§oيسيء الوحل",
  "subtitles.entity.slime.squish": "§4§oسكويشيس الوحل",
  "subtitles.entity.snow_golem.death": "§c§o§lالغولم الثلجي يموت",
  "subtitles.entity.snow_golem.hurt": "§4§oالغولم الثلجي يتأذي",
  "subtitles.entity.snowball.throw": "§7§lكرة الثلج الذباب",
  "subtitles.entity.spider.ambient": "§4§oيهسهس العنكبوت",
  "subtitles.entity.spider.death": "§a§lيموت العنكبوت",
  "subtitles.entity.spider.hurt": "§2§oيسيء العنكبوت",
  "subtitles.entity.squid.ambient": "§8§oيسبح الحبار",
  "subtitles.entity.squid.death": "§a§lيموت الحبار",
  "subtitles.entity.squid.hurt": "§8§oيسيء الحبار",
  "subtitles.entity.squid.squirt": "§7§oالحبار يفرز حبرًا",
  "subtitles.entity.stray.ambient": "§4§oالدلايات شارد",
  "subtitles.entity.stray.death": "§a§lيموت شارد",
  "subtitles.entity.stray.hurt": "§2§oيسيء شارد",
  "subtitles.entity.strider.death": "§c§lStrider يموت",
  "subtitles.entity.strider.eat": "§2§oStrider يأكل",
  "subtitles.entity.strider.happy": "§2§oStrider يغني",
  "subtitles.entity.strider.hurt": "§4§oStrider يتألم",
  "subtitles.entity.strider.idle": "§7§oسترايدر يغرد",
  "subtitles.entity.strider.retreat": "§4§oStrider ينسحب",
  "subtitles.entity.tnt.primed": "§f§o§lتي أن تي فيزيس",
  "subtitles.entity.tropical_fish.death": "§8§o§lسمكة إستوائية تموت",
  "subtitles.entity.tropical_fish.flop": "§8§oسمكة إستوائية تتخبط",
  "subtitles.entity.tropical_fish.hurt": "§8§oسمكة إستوائية تتأذى",
  "subtitles.entity.turtle.ambient_land": "§7§oسقسقة السلحفاة",
  "subtitles.entity.turtle.death": "§c§lموت السلحفاة",
  "subtitles.entity.turtle.death_baby": "§c§lموت صغير السلحفاة",
  "subtitles.entity.turtle.egg_break": "§c§lبيضة السلحفاة تتحطم",
  "subtitles.entity.turtle.egg_crack": "§2§oبيضة السلحفاة تتشقق",
  "subtitles.entity.turtle.egg_hatch": "§a§o§lفقست بيضة السلحفة",
  "subtitles.entity.turtle.hurt": "§4§oالسلحفاة تتأذي",
  "subtitles.entity.turtle.hurt_baby": "§4§oصغير السلحفاة يتأذي",
  "subtitles.entity.turtle.lay_egg": "§a§oالسلحفاة تضع البيض",
  "subtitles.entity.turtle.shamble": "§7§oتمايل السلحفاة",
  "subtitles.entity.turtle.shamble_baby": "§7§oتمايل صغير السلحفاة",
  "subtitles.entity.turtle.swim": "§9§oسباحة السلحفاة",
  "subtitles.entity.vex.ambient": "§4§oإغاظة الفيكس",
  "subtitles.entity.vex.charge": "§c§o§lيصرخ الفيكس",
  "subtitles.entity.vex.death": "§a§lشبح يموت",
  "subtitles.entity.vex.hurt": "§2§oيتأذى الفيكس",
  "subtitles.entity.villager.ambient": "§8§oيغمغم قروي",
  "subtitles.entity.villager.celebrate": "§2§oالقروي يهتف",
  "subtitles.entity.villager.death": "§c§lيموت قروي",
  "subtitles.entity.villager.hurt": "§4§oيسيء قروي",
  "subtitles.entity.villager.no": "§7§oيختلف قروي",
  "subtitles.entity.villager.trade": "§7§oالحرف قروي",
  "subtitles.entity.villager.work_armorer": "§2§oحداد الأسلحة يعمل",
  "subtitles.entity.villager.work_butcher": "§2§oالطباخ يعمل",
  "subtitles.entity.villager.work_cartographer": "§2§oالخرائط تعمل",
  "subtitles.entity.villager.work_cleric": "§2§oرجل الدين يعمل",
  "subtitles.entity.villager.work_farmer": "§2§oالفلاح يعمل",
  "subtitles.entity.villager.work_fisherman": "§2§oالصياد يعمل",
  "subtitles.entity.villager.work_fletcher": "§2§oبائع الأسهم يعمل",
  "subtitles.entity.villager.work_leatherworker": "§2§oعامل الجلود يعمل",
  "subtitles.entity.villager.work_librarian": "§2§oأمين المكتبة يعمل",
  "subtitles.entity.villager.work_mason": "§2§oالعامل البناء يعمل",
  "subtitles.entity.villager.work_shepherd": "§2§oالراعي يعمل",
  "subtitles.entity.villager.work_toolsmith": "§2§oحدادة الأدوات تعمل",
  "subtitles.entity.villager.work_weaponsmith": "§2§oحدادة الأسلحة تعمل",
  "subtitles.entity.villager.yes": "§a§oيوافق على قروي",
  "subtitles.entity.vindicator.ambient": "§4§oيتمتم المتبرئ",
  "subtitles.entity.vindicator.celebrate": "§4§oالمتبرئ يهتف",
  "subtitles.entity.vindicator.death": "§a§lالمتبرئ يموت",
  "subtitles.entity.vindicator.hurt": "§2§oيتأذى المتبرئ",
  "subtitles.entity.wandering_trader.ambient": "§7§oالبائع المتجول يدندن",
  "subtitles.entity.wandering_trader.death": "§c§lالبائع المتجول يموت",
  "subtitles.entity.wandering_trader.disappeared": "§d§oالتاجر المتجول يختفي",
  "subtitles.entity.wandering_trader.drink_milk": "§2§oالتاجر المتجول يشرب الحليب",
  "subtitles.entity.wandering_trader.drink_potion": "§4§oالتاجر المتجول يشرب جرعة سحرية",
  "subtitles.entity.wandering_trader.hurt": "§4§oالبائع المتجول يتأذي",
  "subtitles.entity.wandering_trader.no": "§7§oالبائع المتجول لا يوافق",
  "subtitles.entity.wandering_trader.reappeared": "§b§oظهر التاجر المتجول",
  "subtitles.entity.wandering_trader.trade": "§7§oالبائع المتجول يتبادل",
  "subtitles.entity.wandering_trader.yes": "§a§oالبائع المتجول يوافق",
  "subtitles.entity.witch.ambient": "§4§oالضحك الساحرة",
  "subtitles.entity.witch.celebrate": "§4§oالساحرة تهتف",
  "subtitles.entity.witch.death": "§a§lيموت الساحرة",
  "subtitles.entity.witch.drink": "§c§lالمشروبات الساحرة",
  "subtitles.entity.witch.hurt": "§2§oيسيء الساحرة",
  "subtitles.entity.witch.throw": "§c§lيلقي ساحرة",
  "subtitles.entity.wither.ambient": "§4§0§lالوذز يغضب",
  "subtitles.entity.wither.death": "§b§lالوذر يموت",
  "subtitles.entity.wither.hurt": "§3§oالوذر يتأذي",
  "subtitles.entity.wither.shoot": "§c§lالوذر يهاجم",
  "subtitles.entity.wither.spawn": "§c§o§lالوذر انفجر",
  "subtitles.entity.wither_skeleton.ambient": "§4§oخشخشات الوذر العظمي",
  "subtitles.entity.wither_skeleton.death": "§a§lالوذر العظمي يموت",
  "subtitles.entity.wither_skeleton.hurt": "§2§oالوذر العظمي يتأذي",
  "subtitles.entity.wolf.ambient": "§7§oالسراويل الذئب",
  "subtitles.entity.wolf.death": "§c§lيموت الذئب",
  "subtitles.entity.wolf.growl": "§4§oالهدير الذئب",
  "subtitles.entity.wolf.hurt": "§4§oيسيء الذئب",
  "subtitles.entity.wolf.shake": "§8§oيهز الذئب",
  "subtitles.entity.zoglin.ambient": "§4§oZoglin يزمجر",
  "subtitles.entity.zoglin.angry": "§c§oZoglin يزمجر بغضب",
  "subtitles.entity.zoglin.attack": "§c§lZoglin يهاجم",
  "subtitles.entity.zoglin.death": "§a§lZoglin مات",
  "subtitles.entity.zoglin.hurt": "§2§oZoglin يتأذى",
  "subtitles.entity.zoglin.step": "§4§oهوجلن يخطو",
  "subtitles.entity.zombie.ambient": "§4§oغيبوبة اهات",
  "subtitles.entity.zombie.attack_wooden_door": "§4§o§lالباب يهتز",
  "subtitles.entity.zombie.converted_to_drowned": "§4§oيتحول الزومبي إلى الغارق",
  "subtitles.entity.zombie.break_wooden_door": "§c§o§lالباب ينكسر",
  "subtitles.entity.zombie.death": "§a§lالزومبي يموت",
  "subtitles.entity.zombie.destroy_egg": "§c§lدهس بيضة سلحفاة",
  "subtitles.entity.zombie.hurt": "§2§oالزومبي يتأذي",
  "subtitles.entity.zombie.infect": "§c§o§lالزومبي يفسد",
  "subtitles.entity.zombie_horse.ambient": "§4§oالخيل الزومبي يبكي",
  "subtitles.entity.zombie_horse.death": "§a§lالخيل الزومبي يموت",
  "subtitles.entity.zombie_horse.hurt": "§2§oالخيل الزومبي يتأذي",
  "subtitles.entity.zombie_villager.ambient": "§4§o§lالزومبي القروي يتأوه",
  "subtitles.entity.zombie_villager.converted": "§a§lالزومبي القروي يصرخ",
  "subtitles.entity.zombie_villager.cure": "§2§oالزومبي القروي يمسح أنفه بعد البكاء",
  "subtitles.entity.zombie_villager.death": "§c§lالزومبي القروي يموت",
  "subtitles.entity.zombie_villager.hurt": "§c§oالزومبي القروي يتأذي",
  "subtitles.entity.zombified_piglin.ambient": "§7§oZombified Piglin يهمهم",
  "subtitles.entity.zombified_piglin.angry": "§4§oZombified Piglin يهمهم بغضب",
  "subtitles.entity.zombified_piglin.death": "§a§lZombified Piglin يموت",
  "subtitles.entity.zombified_piglin.hurt": "§c§oZombified Piglin يتألم",
  "subtitles.event.raid.horn": "§c§o§lصوت الأبواق المشؤومة يرتفع",
  "subtitles.item.armor.equip": "§7§o§lإرتداء الدروع",
  "subtitles.item.armor.equip_chain": "§7§o§lتجلجل درع الزرد",
  "subtitles.item.armor.equip_diamond": "§7§o§lكلانجس الدروع الماس",
  "subtitles.item.armor.equip_elytra": "§7§o§lحفيف الألترا",
  "subtitles.item.armor.equip_gold": "§7§o§lكلينكس درع الذهب",
  "subtitles.item.armor.equip_iron": "§7§o§lالحديد الدروع كلانكس",
  "subtitles.item.armor.equip_leather": "§7§o§lالجلود الدروع روستليس",
  "subtitles.item.armor.equip_netherite": "§7§o§lدرع نذرايت يرتطم ببعضه",
  "subtitles.item.armor.equip_turtle": "§7§o§lإرتداء درع السلحفاة",
  "subtitles.item.axe.strip": "§7§oالفأس يخدش",
  "subtitles.item.berries.pick": "§2§oالتوت يفرقع",
  "subtitles.item.book.page_turn": "§7§oحفريات الصفحة",
  "subtitles.item.book.put": "§7§oالكتابات",
  "subtitles.item.bottle.empty": "§7§oقارورة تفرغ",
  "subtitles.item.bottle.fill": "§7§oتملأ زجاجة",
  "subtitles.item.bucket.empty": "§7§oإفراغ دلو",
  "subtitles.item.bucket.fill": "§7§oيملأ دلو",
  "subtitles.item.bucket.fill_fish": "§7§oتم امساك السمكة",
  "subtitles.item.chorus_fruit.teleport": "§d§lلاعب ينتقل",
  "subtitles.item.crop.plant": "§8§oالمحاصيل المزروعة",
  "subtitles.item.crossbow.charge": "§f§lتعبئة قوس النشاب",
  "subtitles.item.crossbow.hit": "§f§lسهم يصيب",
  "subtitles.item.crossbow.load": "§f§lقوس النشاب عبء",
  "subtitles.item.crossbow.shoot": "§f§lقوس النشاب يحرق",
  "subtitles.item.firecharge.use": "§f§lWhooshes كرة من اللهب",
  "subtitles.item.flintandsteel.use": "§f§lاحتكاك حديد وصوان",
  "subtitles.item.hoe.till": "§8§oمجرفة يستغلها",
  "subtitles.item.honey_bottle.drink": "§2§oبلْع",
  "subtitles.item.lodestone_compass.lock": "§e§lبوصلة حجر المغناطيس مقفولة بتجاهه",
  "subtitles.item.nether_wart.plant": "§3§oالمحاصيل المزروعة",
  "subtitles.item.shears.shear": "§8§oانقر فوق المقص",
  "subtitles.item.shield.block": "§7§o§lدرع يصد هجمة",
  "subtitles.item.shovel.flatten": "§8o§يسطح مجرفة",
  "subtitles.item.totem.use": "§b§o§lينشط الطوطم",
  "subtitles.item.trident.hit": "§f§oطعنات الرمح",
  "subtitles.item.trident.hit_ground": "§f§oإهتزاز الرمح",
  "subtitles.item.trident.return": "§e§lعودة الرمح",
  "subtitles.item.trident.riptide": "§e§oإندفاع الرمح",
  "subtitles.item.trident.throw": "§f§oرمي الرمح",
  "subtitles.item.trident.thunder": "§e§o§lرعد الرمح",
  "subtitles.particle.soul_escape": "§3§oهروب الروح",
  "subtitles.ui.cartography_table.take_result": "§e§oالخريطة المرسومة",
  "subtitles.ui.loom.take_result": "§7§oتستخدم أداة تشكيل الانماط",
  "subtitles.ui.stonecutter.take_result": "§7§oتستخدم أداة قطع الحجارة",
  "subtitles.weather.rain": "§1§oالمطر يسقط"
}
